context_goodies.py
context_goodies-0.1.dist-info/licenses/LICENSE
context_goodies-0.1.dist-info/METADATA
context_goodies-0.1.dist-info/WHEEL
context_goodies-0.1.dist-info/top_level.txt
context_goodies-0.1.dist-info/RECORD
