Metadata-Version: 2.4
Name: context-goodies
Version: 0.1
Author-email: Marcin Bachry <hegel666@gmail.com>
Requires-Python: >=3.12
License-File: LICENSE
Provides-Extra: dev
Requires-Dist: gevent; extra == "dev"
Requires-Dist: pytest; extra == "dev"
Requires-Dist: pytest-cov; extra == "dev"
Requires-Dist: types-gevent; extra == "dev"
Dynamic: license-file
